setup.py
algcore/NetWorkTest.py
algcore/__init__.py
algcore.egg-info/PKG-INFO
algcore.egg-info/SOURCES.txt
algcore.egg-info/dependency_links.txt
algcore.egg-info/top_level.txt