Metadata-Version: 1.0
Name: algcore
Version: 0.3
Summary: algorithm tool and sdk
Home-page: UNKNOWN
Author: vita.wang
Author-email: 2508000696@qq.com
License: UNKNOWN
Platform: UNKNOWN
